<?xml version="1.0" encoding="UTF-8"?>
<OrbitPlannerVisitImpl>
  <OpToolDataDate>
    <Time>1605569411341</Time>
  </OpToolDataDate>
  <TransVersion>20200619</TransVersion>
  <NumRows>1</NumRows>
  <RowDuration>5715</RowDuration>
  <diagnostics />
  <Members>
    <OrbitMemberExposure>
      <startTime>393</startTime>
      <duration>242</duration>
      <timeLineRow>1</timeLineRow>
      <layer>0</layer>
      <subtype>external</subtype>
      <exposureKey>-161</exposureKey>
      <exposureNum>1</exposureNum>
      <exposureTime>1.0</exposureTime>
      <features>
        <Feature>target-acq</Feature>
      </features>
      <targetName>V-EG-UMA</targetName>
      <ra>183.9337417983016</ra>
      <dec>52.51702394313436</dec>
      <config>STIS/CCD</config>
      <opmode>ACQ</opmode>
      <apertures>
        <aperture>F28X50LP</aperture>
      </apertures>
      <spectralElements>
        <specEl>MIRROR</specEl>
      </spectralElements>
      <alignmentTime>242</alignmentTime>
      <alBegin>0</alBegin>
      <alEnd>0</alEnd>
      <endOverhead>0</endOverhead>
    </OrbitMemberExposure>
    <OrbitMemberPcsAcq>
      <startTime>5598</startTime>
      <duration>510</duration>
      <timeLineRow>0</timeLineRow>
      <layer>0</layer>
      <subtype>acq</subtype>
    </OrbitMemberPcsAcq>
    <OrbitMemberExposure>
      <startTime>655</startTime>
      <duration>242</duration>
      <timeLineRow>1</timeLineRow>
      <layer>0</layer>
      <subtype>external</subtype>
      <exposureKey>-170</exposureKey>
      <exposureNum>2</exposureNum>
      <exposureTime>1.0</exposureTime>
      <features>
        <Feature>target-acq</Feature>
      </features>
      <targetName>V-EG-UMA</targetName>
      <ra>183.9337417983016</ra>
      <dec>52.51702394313436</dec>
      <config>STIS/CCD</config>
      <opmode>ACQ/PEAK</opmode>
      <apertures>
        <aperture>52X0.1</aperture>
      </apertures>
      <spectralElements>
        <specEl>MIRROR</specEl>
      </spectralElements>
      <alignmentTime>242</alignmentTime>
      <alBegin>0</alBegin>
      <alEnd>0</alEnd>
      <endOverhead>0</endOverhead>
    </OrbitMemberExposure>
    <OrbitMemberPointingManeuver>
      <startTime>635</startTime>
      <duration>20</duration>
      <timeLineRow>1</timeLineRow>
      <layer>0</layer>
      <subtype>sam</subtype>
    </OrbitMemberPointingManeuver>
    <OrbitMemberDump>
      <startTime>897</startTime>
      <duration>39</duration>
      <timeLineRow>1</timeLineRow>
      <layer>0</layer>
      <subtype>DUMP STIS Buffer</subtype>
    </OrbitMemberDump>
    <OrbitMemberReadout>
      <startTime>897</startTime>
      <duration>39</duration>
      <timeLineRow>1</timeLineRow>
      <layer>0</layer>
    </OrbitMemberReadout>
    <OrbitMemberHome>
      <startTime>936</startTime>
      <duration>262</duration>
      <timeLineRow>1</timeLineRow>
      <layer>0</layer>
      <subtype>overhead</subtype>
    </OrbitMemberHome>
    <OrbitMemberExposure>
      <startTime>1198</startTime>
      <duration>299</duration>
      <timeLineRow>1</timeLineRow>
      <layer>0</layer>
      <subtype>internal</subtype>
      <NotesProperty>
        <note>STIS Auto-WAVECAL</note>
        <note>Auto-WAVECAL</note>
      </NotesProperty>
      <exposureNum>3</exposureNum>
      <exposureTime>65.0</exposureTime>
      <wavelength>1222.0</wavelength>
      <targetName>WAVE</targetName>
      <config>STIS/FUV-MAMA</config>
      <opmode>ACCUM</opmode>
      <apertures>
        <aperture>52X0.1</aperture>
      </apertures>
      <spectralElements>
        <specEl>G140M</specEl>
      </spectralElements>
      <alignmentTime>299</alignmentTime>
      <alBegin>0</alBegin>
      <alEnd>0</alEnd>
      <endOverhead>0</endOverhead>
    </OrbitMemberExposure>
    <OrbitMemberDump>
      <startTime>1497</startTime>
      <duration>57</duration>
      <timeLineRow>1</timeLineRow>
      <layer>0</layer>
      <subtype>DUMP STIS Buffer</subtype>
    </OrbitMemberDump>
    <OrbitMemberReadout>
      <startTime>1497</startTime>
      <duration>57</duration>
      <timeLineRow>1</timeLineRow>
      <layer>0</layer>
    </OrbitMemberReadout>
    <OrbitMemberExposure>
      <startTime>1554</startTime>
      <duration>1388</duration>
      <timeLineRow>1</timeLineRow>
      <layer>0</layer>
      <subtype>external</subtype>
      <exposureKey>-181</exposureKey>
      <exposureNum>3</exposureNum>
      <exposureTime>1358.0</exposureTime>
      <wavelength>1222.0</wavelength>
      <targetName>V-EG-UMA</targetName>
      <ra>183.9337417983016</ra>
      <dec>52.51702394313436</dec>
      <config>STIS/FUV-MAMA</config>
      <opmode>TIME-TAG</opmode>
      <apertures>
        <aperture>52X0.1</aperture>
      </apertures>
      <spectralElements>
        <specEl>G140M</specEl>
      </spectralElements>
      <alignmentTime>1388</alignmentTime>
      <alBegin>0</alBegin>
      <alEnd>0</alEnd>
      <endOverhead>0</endOverhead>
    </OrbitMemberExposure>
    <OrbitMemberDump>
      <startTime>2942</startTime>
      <duration>178</duration>
      <timeLineRow>1</timeLineRow>
      <layer>0</layer>
      <subtype>DUMP STIS Buffer</subtype>
    </OrbitMemberDump>
    <OrbitMemberReadout>
      <startTime>2942</startTime>
      <duration>178</duration>
      <timeLineRow>1</timeLineRow>
      <layer>0</layer>
    </OrbitMemberReadout>
    <OrbitMemberHome>
      <startTime>3120</startTime>
      <duration>262</duration>
      <timeLineRow>1</timeLineRow>
      <layer>0</layer>
      <subtype>overhead</subtype>
    </OrbitMemberHome>
    <OrbitMemberOccultation>
      <startTime>2942</startTime>
      <duration>2773</duration>
      <timeLineRow>1</timeLineRow>
      <layer>0</layer>
    </OrbitMemberOccultation>
    <OrbitMemberUnusedVis>
      <startTime>2942</startTime>
      <duration>0</duration>
      <timeLineRow>1</timeLineRow>
      <layer>0</layer>
      <Overrun>false</Overrun>
    </OrbitMemberUnusedVis>
  </Members>
</OrbitPlannerVisitImpl>
